admin_export_action/__init__.py
admin_export_action/admin.py
admin_export_action/config.py
admin_export_action/introspection.py
admin_export_action/models.py
admin_export_action/report.py
admin_export_action/urls.py
admin_export_action/views.py
admin_export_action/locale/es/LC_MESSAGES/django.mo
admin_export_action/locale/es/LC_MESSAGES/django.po
admin_export_action/locale/it/LC_MESSAGES/django.mo
admin_export_action/locale/it/LC_MESSAGES/django.po
admin_export_action/locale/pt/LC_MESSAGES/django.mo
admin_export_action/locale/pt/LC_MESSAGES/django.po
admin_export_action/locale/ru/LC_MESSAGES/django.mo
admin_export_action/locale/ru/LC_MESSAGES/django.po
admin_export_action/locale/zh_Hans/LC_MESSAGES/django.mo
admin_export_action/locale/zh_Hans/LC_MESSAGES/django.po
admin_export_action/templates/export_action/export.html
admin_export_action/templates/export_action/fields.html
admin_export_action/templates/export_action/report_html.html
django_admin_export_action-0.3.3.dist-info/licenses/LICENSE
django_admin_export_action-0.3.3.dist-info/METADATA
django_admin_export_action-0.3.3.dist-info/WHEEL
django_admin_export_action-0.3.3.dist-info/top_level.txt
django_admin_export_action-0.3.3.dist-info/RECORD
