Metadata-Version: 2.4
Name: django-admin-export-action
Version: 0.3.3
Summary: Export action for django admin
Home-page: http://github.com/otto-torino/django-admin-export-action
Author: abidibo
Author-email: abidibo@gmail.com
License: MIT License
Project-URL: Documentation, http://github.com/otto-torino/django-admin-export-action/blob/master/README.md
Project-URL: Source, http://github.com/otto-torino/django-admin-export-action
Project-URL: Tracker, http://github.com/otto-torino/django-admin-export-action/issues
Classifier: Development Status :: 5 - Production/Stable
Classifier: Environment :: Web Environment
Classifier: Framework :: Django
Classifier: Intended Audience :: Developers
Classifier: Intended Audience :: System Administrators
Classifier: License :: OSI Approved :: MIT License
Classifier: Operating System :: OS Independent
Classifier: Programming Language :: Python
Classifier: Programming Language :: Python :: 2.7
Classifier: Programming Language :: Python :: 3.2
Classifier: Programming Language :: Python :: 3.3
Classifier: Programming Language :: Python :: 3.5
Classifier: Programming Language :: Python :: 3.6
Classifier: Programming Language :: Python :: 3.7
Classifier: Programming Language :: Python :: 3.8
Classifier: Programming Language :: Python :: 3.9
Classifier: Programming Language :: Python :: 3.10
Classifier: Programming Language :: Python :: 3.11
Classifier: Topic :: Software Development
License-File: LICENSE
Requires-Dist: openpyxl
Dynamic: author
Dynamic: author-email
Dynamic: classifier
Dynamic: description
Dynamic: description-content-type
Dynamic: home-page
Dynamic: license
Dynamic: license-file
Dynamic: project-url
Dynamic: requires-dist
Dynamic: summary
